corva_otel/faas/__init__.py
corva_otel/faas/otel_faas_wrap.py
corva_otel_faas-0.2.2.dist-info/METADATA
corva_otel_faas-0.2.2.dist-info/WHEEL
corva_otel_faas-0.2.2.dist-info/RECORD
